{
  "chunk_id": 1365,
  "text": "particular company, for exam- ple, then discovering to one\u2019s horror that the company was knowingly and without remorse allowing its employees to be poisoned, while fully intending to dismiss them with no accountability for assisting with the medical bills. Or perhaps, discovering that your spouse had not only been \u201chaving an affair\u201d, but had been conspiring with the \u201cother\u201d to have you killed so they could collect the insurance policy. A rude and painful awakening occurs when you discover that things you have believed in for a very long time, things perhaps you have built your life around, have never been what they appeared to be, but rather an expertly crafted pack of lies created to harm and enslave you. When we desire to \u201cknow the truth\u201d, and then the truth is revealed, what do we do if it is not the truth we wanted to hear? As the GA dispensations continued following the initial revelations of the Treaty of Altair, I realized how grateful I was to finally understand, yet I also acknowledge how \u201cKnowing\u201d has suddenly and forcefully \u201cburst my bubble\u201d of na\u00efvet\u00e9 concerning the type of world within which we presently live. At least in America, a country that until recently had not witnessed the tragadies of major airborne war on its mainland territories, we seem to be raised with a few cultural blind spot in which we come to believe that \u201cOh, it couldn\u2019t be that bad\u201d, or \u201cThat",
  "metadata": {
    "chunk_index": 1,
    "source": "voyagers_2",
    "page": 262
  }
}