{
  "chunk_id": 2202,
  "text": "sland 371-372 Easter Island Heads 371 EBE 173, 178 Eckatic Codes 272 E-Den 2 Eden, Garden of 6 education 37 ego 79-81 origins of 81 Egypt 36, 56, 60, 62, 71, 88, 103, 313, 320, 322 as resettlement for Atlantis survivors 63 Egyptian 28, 46, 74, 239, 461 Invasion 330 mystery schools 15 Pharaonic line 47 see also Pharaoh Egyptian Invasion 321 Eieyani 270, 319, 372 Massacre 311, 319, 330, 372 Electric Wars 18, 22, 45, 51, 251 end of 19 electrical disruption 182 Elohei-Elohim 242, 369 Human Guardian race 243 Oraphim 267 Elohim 2, 3, 4, 6, 18-27, 34, 43, 46, 50, 55, 57, 59, 62, 66, 69, 75, 76, 83, 87, 91-104, 122, 193,194",
  "metadata": {
    "source": "voyagers_2",
    "chunk_index": 2,
    "page": 581
  }
}