{
  "chunk_id": 1775,
  "text": "ot told these sites were ''Anunnaki intended take-over points.'' They were told the lie that these sites were ''sacred and belonged to their Creator Gods and Angels.'' Since the 9558 BC \u201cfall of Atlantis,\u201d churches, synagogues, places of ''worship,'' economic, governmental, and public social areas were repeatedly built over, and around, areas through which the Phoenix Spiking Matrix would be run come the 2000-2017 SAC. Many of the Phoenix Matrix territories were overtaken by competing Drakonian agenda Leviathan Illuminati forces, who would usually destroy the buildings of their competitors and erect their own edifices to their Fallen Angelic effigies. At various times, the Anunnaki Fallen Angelics of Nibiru, Tiamat and Alcyone would use their Phoenix Matrix, NDC-Grid and NET, to Cap the Falcon Matrix wormhole of their Drakonian competitors. The Drakonian Illuminati would then quest for the territories of the Nibiruian Crystal Temple Network, successfully gain governing control over some of the 24 Primary sites and use them to siphon energy from the NDC-Grid in order to '' blow the Cap back off'' of the Falcon wormhole. Anunnaki and 398",
  "metadata": {
    "chunk_index": 2,
    "source": "voyagers_2",
    "page": 411
  }
}