{
  "chunk_id": 2158,
  "text": "UIR, \u201cWingmakers\u201d, the Labyrinth Weapon and 2011 evacuations and to protect the 12 Primary Cue Site entrances to the Inner Earth Halls of Amenti control temples. Intensive \u201cStar Wars\u201d would break out in Earth\u2019s skies and regional galaxies, with earthly nations caught in the crossfire, as UIR and competing rebel Omicron-Drakonian \ufb02eets from Phantom Matrix poured into Earth\u2019s local galaxies. Though Emerald Covenant \ufb02eets would succeed in preventing UIR takeover of the Inner Earth Halls of Amenti control sites, the Planetary Christos Realignment Mission and Level-12 Planetary Maharic Seal could not be fulfilled due to further damage to Earth\u2019s Planetary Shields. Human civilization on Earth would again be decimated, as it has been several times in the past, and major intergalactic wars would again break out as they did 550 million, 30 million, 5.5 million and 4.5 million years ago. The 2011 period of weak- ness in Earth\u2019s Meajh\u00e9 Zones is anticipated to begin between April-July 2011, and will last for a 3 to 4 month period, into August or latest Nov of 2011. UIR has their final con- quest invasion strategy underway, but so too do Emerald Covenant nations have their counter-strategy in place. UIR, \u201cWINGMAKERS\u201d THE LABYRINTH WEAPON AND 2011 A collective of renegade Necromiton-Andromie/Jehovian Anunnaki hybrid Nephilim races, now members of the UIR, have been initiating progressive cov",
  "metadata": {
    "page": 566,
    "source": "voyagers_2",
    "chunk_index": 0
  }
}