{
  "chunk_id": 1527,
  "text": "15 The Atlantian Conspiracy and Roundtables LONG-TERM PROBLEMS AND IMMEDIATE SOLUTIONS Rainbow Roundtables \u2022 The Sacred Science Mechanics by which the Planetary Christos Realign- ment can be fulfilled have long been hidden within the Legends of King Arthur and the ''Knights of the Roundtable.'' \u2022 The ''Roundtable'' of Arthurian Legend referred to Signet Councils. The word \u201cSignet\u201d refers to ''Star Gates.'' In the ancient knowledge of the Palaidia Urtite-Cloister races, the Signet Councils were the specific groups of Angelic Humans that assembled to run the corrected Fire Let- ter Sequences into Earth\u2019s Planetary Shields during SACs, to prevent pole shift and progressively restore Earth\u2019s D-12 Christos Divine Blue- print (the Shield of Aramatena). \u2022 The \u201cRoundtable\u201d of Arthurian Legend referred to the \u201cRainbow Round- table\u201d (RRT). The RRTs are groups of Angelic Humans assembled in the 4 Evolutionary Rounds who are commissioned to run the \u201cRainbow Ray\u201d or \u201cKhundaray\u201d Primal Sound Current from beyond the 15-Di- mensional Time Matrix, into Earth\u2019s Planetary Shields during SACs. Running of the Rainbow Ray during SACs enables the planet to retain its natural electromagnetic balances to avert pole shift and restores the or- ganic D-12 Planetary Christos Alignment. \u2022 Since the 9558 BC Atlantian Flood, knowledge of the RRTs has been in- tentionally hidden from the Angelic Human races of",
  "metadata": {
    "chunk_index": 0,
    "page": 323,
    "source": "voyagers_2"
  }
}