{
  "chunk_id": 1,
  "text": "Voyagers The Sleeping Abductees Volume I of the Emerald Covenant CDT-Plate Translations Ashayana Deane, (formerly published as Anna Hayes) Published by Wild Flower Press, an imprint of Granite Publishing L.L.C., at Smashwords First Smashwords Edition Information Transcribed from the Guardian Alliance regarding Extraterrestrial Visitation, the Extraterrestrial Agendas, Keylontic Morphogenetic Science, and the Mechanics of Alien Contact. These transcriptions are not derived from channeled sources. Wild Flower Press Copyright 2011 by Ashayana Deane First Smashwords Edition License Notes This ebook is licensed for your personal enjoyment only. This ebook may not be re-sold or given away to other people. If you would like to share this book with another person, please purchase an additional copy for each person you share it with. If you're reading this book and did not purchase it, or it was not purchased for your use only,",
  "metadata": {
    "chunk_index": 0,
    "page": 3,
    "source": "voyagers_1"
  }
}