{
  "chunk_id": 854,
  "text": "s and con- sciousness embodiment of the God-force. They did not teach that God was a male authority \ufb01gure who passed judgment upon sinful, inferior humans. They did not teach that the male gender was formed in the image of God and the female was a lesser part extracted through the godly male to hold a position of subservience to men. The original Templar creed did not endorse the exploi- tation of the plant, animal and mineral kingdoms for the purpose of personal sustenance and materialistic gain, it taught respect and reverence for all life. The original Templar did not teach of \u201cgood and evil\u201d; it taught that evil deeds were the result of ignorance to the true structure of the universe, and that evil was cured by education through the Law of One. It taught that peo- ples were created to be free, and in that freedom should be taught how to become co-creators with the God-force. It taught that every being in the universe was an individual face and expression of God, and that brotherhood was simply the rational result of this comprehension. Literally all of the elitist, sexist, materialistic distortions to the true Laws of the Templar were perpetrated through the in\ufb02uence of the Anunnaki Resistance, some of their ET co-conspirators and the Templar-Annu Resistance loyalists lin- eage who became their earthly operatives. The distorted Templar creeds moti- vated everything from the",
  "metadata": {
    "source": "voyagers_2",
    "page": 81,
    "chunk_index": 1
  }
}