{
  "chunk_id": 1875,
  "text": "ce to protect from Red Pulse & begin genetic repair abductions 1973:Guardians begin infusions of energy on sun to repair solar damage from Zetas 1943 sun manipulations 1973 -1/11/1992: Guardians employ Holographic Inserts to maintain illusion of Earth stability while sun realigns 1982: Guardians split and divert course of asteroid due to hit Earth. 1982-1984: Most Zeta groups enter Guardian treaties & stop take-over plan Dracos-Zeta Resistance refuses 8/12/1983: Dracos-Zetas instigate Montauk Project, create 2 nd space-time rip & begin creating clones and infiltrates 1984: Guardians discover 2976 AD Earth destruction as result of Zeta infiltration, create Bridge Zone Project 10/1986: 1 st Seal on Arc of Covenant opens, Sphere of Amenti begins descent; 9540 BC Frequency Fence lifts 8/16/1987: Harmonic Convergence. Guardians granted permission to activate Bridge Zone Project intervention 1/1988: Sphere of Amenti returns to Earth. Earth's 1 st primary V ortex -Arizona USA - opens. 9/1989: Guardians finish repair of Solar Fields 8 & begin infusions of D-4 frequency to Earth, to raise core vibration 1/11/1992: Guardians reenter 11:11 magnetic codes to Earth core, 11:11/12.12 Frequency Fence begins release 6/1992: Earth's 2 nd primary V ortex - Jerusalem, Israel - opens. 7/26/1992: Avatar 1 of Six Silent Ascension Avatars is born; 7th level avatar 12/12/1994: 11:11/12:12 Frequency Fe",
  "metadata": {
    "chunk_index": 1,
    "page": 448,
    "source": "voyagers_2"
  }
}