{
  "chunk_id": 586,
  "text": "many Emerald Covenant Speakers that came before him, have tried to bring this truth to us and demonstrate its power; so that we, as the Guardian Christiac Angelic Race that we are, might finally re-awaken to set ourselves, our Souls and our planet free from the illusion of mortal limitation and the manipulation of Fallen Angelic dominion. 2000 years ago humanity was faced with a choice of allowing the Inner Christos to lead us home, or to Crucify the Inner Christ that Jesheua-Jesus modeled for us through the worship of externalized God- personifications. We are faced with this same choice again between 2000-2017, and the Fallen Angelic Legions will do their best to provide us with all opportunity to make a misinformed decision. On behalf of the Yanas from beyond the Time Matrix, the Density-5 MC Eieyani Masters Council, Founders Races, the Azurite Universal Templar Security Team, Eieyani Priests of Ur, IAFW, GA and Guardian Angelic Races of the Emerald Covenant, and in support of the causes of Angelic Human freedom and the continued healing and survival of Earth, GA Signet Council-6, the Council of Azurline, guardians of Sirius B Star Gate-6 and progenitors of the Indigo Children Eieyani- Christiac Angelic Human race line presently incarnate on Earth, are revealing this historical information pertaining to the \u201cChrist Story\u201d and Pre-ancient Angelic Human evolution because, the",
  "metadata": {
    "chunk_index": 0,
    "page": 272,
    "source": "voyagers_1"
  }
}