{
  "chunk_id": 1891,
  "text": "pment of humans within the Bridge Zone Earth. The success of the ascension program is dependent upon the births of the six Silent Ascension Avatars proceeding according to schedule. They are called the Silent Avatars because their identities, religious affiliations and geographical locations will be undisclosed to the public during the ascension period. Their identities will not be revealed until they have reached the age of 33 and their service mis- sions come into mass awareness. 446",
  "metadata": {
    "chunk_index": 2,
    "source": "voyagers_2",
    "page": 459
  }
}