{
  "chunk_id": 563,
  "text": "rsal Templar Security Team, and remaining Emerald Covenant loyal members of the Arcturian Federation of Planets still hold Arcturus Star Gate-7 under Guardian Angelic protection. In September 2000, Annu-Elohim Fallen Angelic members of the Arcturian Federation of Planets launched a conquest to seize control of the D-7 Arcturus Star Gate-7. The results of this campaign are yet to be determined. GA Signet Council-6, Sirius B, Indigo Children And \u201cChristiac Grail Lines\u201d The 6 remaining GA Signet Councils that protect Universal Star Gates 1 through 6 in the Densities 1 and 2 (dimensions 1-6) systems operate under the direct supervision of the MC Eieyani Master Council (\u201cSirian or Azurite\u201d Council) of Density-5. The MC Eieyani Council attends directly to the needs of the 6 Signet Councils in the lower- dimensional Densities, through their incarnate representatives in the Sirius B Azurite and Oraphim Angelic Human Eieyani race lines. Though the MC Eieyani Master Council oversees all IAFW activities from the Density-5 Primal Light Fields, they directly intervene when needed in distressed areas of the Time Matrix. Since the restatement of the Emerald Covenant 570 million years ago, and subsequent creation of the GA, Guardian Oraphim Angelic Human and avenging Anunnaki",
  "metadata": {
    "chunk_index": 1,
    "page": 260,
    "source": "voyagers_1"
  }
}