{
  "chunk_id": 530,
  "text": "e or skeptical attitude such as \u201cprove it to me,\u201d you are operating out of a belief that the dynamics of the exercises are false. Just as in the case of dream recall, your ideas about the subject will serve to enable or block the process. A skeptical attitude will translate on a subconscious level into a subliminal command that orders the biological suppression of the experiences and memory that would reveal to you the true validity of these dynamics. For this reason we suggest using these exercises only after you have cultivated an open attitude and sincere curiosity, for with an open attitude you are far more likely to achieve the results that will allow you to prove to yourself the realities of which we speak. The coming period of 2012-2017 marks a time of physical and bio-energetic changes on Earth that are unprecedented in recorded human history. Developing skills in technologies of mind and applied Keylontic Morphogenetic Science will assist you to create adaptability of body and consciousness. We hope that you will enjoy the exercises we have provided in this book and that you will use them to your own advantage, to further accelerate your Soul Integration process. Through Soul Integration your race will take its next evolutionary step toward biological and spiritual maturity, to one day emerge within the realms of pure knowing and At-one-ment with the eternal creative S",
  "metadata": {
    "source": "voyagers_1",
    "chunk_index": 1,
    "page": 244
  }
}