{
  "chunk_id": 97,
  "text": "emerge from free-will choices rendered in our present space-time continuum. (Of the existing \u201cprobable futures,\u201d or Primary Time Vectors of evolutionary development that exist as \u201cfuture\u201d experiential potentials, our present moment choices determine which line of probable evolution we will perceive in manifest form as a future continuum of time emerging from our present space-time coordinate.) Most valuable to our present time, the CDT-Plates contain extensive educational records pertaining to Founders Race Creation Mechanics, \u201cUniversal Unified Field Physics,\u201d and \u201cLaw of One\u201d\u2014\u201cInner Christ\u201d Sacred Spiritual-Science \u201cAscension-Merkaba\u201d training. The CDT-Plates also contain the history and details of the Founders\u2019 Emerald Covenant Co-evolution Agreement peace treaty, humanity's historical relationship to the Emerald Covenant. As designated by the Emerald Covenant restatement of 246,000 BC, the CDT-Plates contain the teachings of Masters Templar Mechanics (Planetary, Galactic and Universal Star Gate mechanics), DNA Template Bio-Regenesis and Kathara Core Template Healing technologies. These masters' teachings were originally provided to the Angelic Human race of Earth in order for humanity to fulfill its original \u201cCreation Commission\u201d as guardians and keepers of the Universal Templar Complex.",
  "metadata": {
    "page": 50,
    "chunk_index": 1,
    "source": "voyagers_1"
  }
}