{
  "chunk_id": 2085,
  "text": "2001 Update Summary charts Phantom Matrix Anunnaki Intruder Races \u2022 Marduke-Luciferian-Anunnaki: (Fallen Anu-Seraphim hybrid, Lyra Aveyon) Phantom Alpha/Omega Centauri, Nibiru, Tiamat. APIN System: NDC-Grid/NCT-Bases/NET, Phoenix, Serpent Nibiruian APINs. Primary Races: - Vichoritz insectoid-serpent-hominid (Thoth-Enki Lulitan family-Amealian-Anunnaki/Marduke Satain family-Amealian -Anunnaki/Necromiton- Andromie hybrid) and Vichor Light-haired Humanoid (Pleiadian-Amealian-Anunnaki/Vichoritz hybrid) Nibiru, Tiamat, Alpha Centauri. Centaur-Luciferians Hominid-Centaur hybrids (Vichoritz-Centaur) Alpha Centaur. Core Agenda: Luciferian-Anunnaki Pleiadian-Nibiruian Coalition and/or Necromiton-Andromie Orion- Necromiton Black League. Primary Leviathan Illuminati Races: Elucum King/ Beli-Kadmon Atalan King Atlantian Leviathan Illuminati lines. Babylonian-Sumerian Vicherous King (Elucum King-Druedic Maji hybrid) \u201cScandinavian Vi-Kings\u201d, Hyksos King Knights T emplar/Freemason Master Race Leviathan Illuminati lines. Human Tribe In\ufb01ltration: Raided Tribe-3 Druedic Maji lines Nohasa Atlantis/ Scandinavia/ England/Ireland/Scotland, Scots \u201cMcGregor\u201d raider lines, Knights Templar Freemasons. Associations: 9560BC Luciferian Covenant. Work with Pleiadian-Samjase-Luciferian-Anunnaki/ Nibiruian Thoth-Enki-Zephelium-Anunnaki and/or Centaur Luciferian/ Necromiton-Andromie Orion-Necromiton Black Leag",
  "metadata": {
    "chunk_index": 0,
    "page": 548,
    "source": "voyagers_2"
  }
}