{
  "chunk_id": 1382,
  "text": "The D-12 Planetary Security Seal, Planetary Shields... THE D-12 PLANETARY SECURITY SEAL, PLANETARY SHIELDS CLINICS, AND CRISIS INTERVENTION If GA forces had demonstrated a show of power through orchestrating a mass contact drama to warn humans of the Anunnaki and Drakonian intentions, the Anunnaki intended to abort their desired outcome of strategi- cally using humans to \u201copen the Amenti Gates\u201d, and would settle instead for destroying contemporary humans via immediate pole shift, while capturing a few humans as potential enslaved \u201cGate Code breeders\u201d. The Anunnaki legions, as well as the Drakonian legions, have long understood that if humanity became awakened, the Fallen Angelic Amenti dominion plan would rapidly come to a screeching halt. Humanity has a hidden power within the DNA Template, through which the innate Planetary Star Gate Security Codes can be used to trigger activation of a natural 12-Dimensional Planetary Security Seal within Earth\u2019s Templar, which if successfully erected, would permanently protect Earth\u2019s portals and Star Gates from any further Fallen Angelic infiltration. Humans are the greatest threat to the Fallen Angelic agenda, and for this reason they have gone to great lengths to ensure our genetically-induced race amnesia and our ignorance to the Sacred Sci- ence Physics knowledge through which humanity can regain its intended guardianship of Earth\u2019s Te",
  "metadata": {
    "source": "voyagers_2",
    "chunk_index": 0,
    "page": 268
  }
}