{
  "chunk_id": 956,
  "text": "he teachings of the sacred Law of One. Though Jesheua-12 had successfully aligned the race morphogenetic field at Amenti with the original 12-strand DNA imprint, most of the races still carried traces of genetic distortions from the Templar and Templar- Axion Seals, which would need to be cleared prior to the opening of the Halls of Amenti. The Elohim, Templar Melchizedeks, Blue Flame Melchizedeks and many other unrelated Host Matrix groups have assisted, and continue to assist, many individuals in clearing their genetic codes in preparation for ascension. All present-day ideologies that teach conscious evolu- tion, and DNA activation and transmutation, are geared toward this purpose, including the new information currently being provided by various guardian ET and metaterrestrial forces. Jesheua-12, the 12th-level Turaneusiam avatar from Tara, fulfilled his purposes on Earth. Through him the Sphere of Amenti was made ready for re-entry into Earth\u2019s core, following which the Halls of Amenti would eventually be opened. The race morphogenetic field had been reunited, so following the opening of the Halls of Amenti, all souls could again ascend through Amenti, once their genetic imprint had evolved to assemble the fourth and fifth DNA strand. The plan for preparing the races for the 2017 AD ascension wave was put back on schedule. Since 27 AD, when the avatar Jesheua-12 ascended,",
  "metadata": {
    "chunk_index": 1,
    "page": 117,
    "source": "voyagers_2"
  }
}